_dynet.cpython-36m-darwin.so
dynet.py
dynet_config.py
dynet_viz.py
libdynet.dylib
dyNET-2.1.2.dist-info/METADATA
dyNET-2.1.2.dist-info/WHEEL
dyNET-2.1.2.dist-info/top_level.txt
dyNET-2.1.2.dist-info/RECORD
